cobaltstrike/__init__.py
cobaltstrike-0.0.2.dist-info/LICENSE
cobaltstrike-0.0.2.dist-info/METADATA
cobaltstrike-0.0.2.dist-info/WHEEL
cobaltstrike-0.0.2.dist-info/entry_points.txt
cobaltstrike-0.0.2.dist-info/top_level.txt
cobaltstrike-0.0.2.dist-info/RECORD
