Metadata-Version: 2.1
Name: cobaltstrike
Version: 0.0.2
Summary: CobaltStrike Python API
Home-page: https://blog.cobaltstrike.com
Author: xlzd
Author-email: cs@gmail.com
License: UNKNOWN
Platform: UNKNOWN
